[
  {
    "id": "shishak",
    "name": "שישק מלך מצרים",
    "empire": "מצרים",
    "power": "egypt",
    "start": 2958,
    "end": 2982,
    "source": "מלכים א י\"ד",
    "description": "בשנה החמישית לרחבעם עלה על ירושלים ובזז את אוצרות בית המקדש ובית המלך."
  },
  {
    "id": "tiglat-pileser",
    "name": "תגלת פלאסר (פול) מלך אשור",
    "empire": "אשור",
    "power": "assyria",
    "start": 3150,
    "end": 3187,
    "source": "מלכים ב ט\"ו",
    "description": "לקח מס ממנחם מלך ישראל, ובימי פקח הגלה את הגליל ואת עבר הירדן — הגלות הראשונה של ישראל."
  },
  {
    "id": "shalmaneser",
    "name": "שלמנאסר מלך אשור",
    "empire": "אשור",
    "power": "assyria",
    "start": 3187,
    "end": 3207,
    "source": "מלכים ב י\"ז",
    "description": "צר על שומרון שלוש שנים; בשנת 3205 נפלה העיר ועשרת השבטים הוגלו — סוף ממלכת ישראל."
  },
  {
    "id": "sancheriv-w",
    "name": "סנחריב מלך אשור",
    "empire": "אשור",
    "power": "assyria",
    "start": 3207,
    "end": 3225,
    "source": "מלכים ב י\"ח–י\"ט; ישעיהו ל\"ו–ל\"ז",
    "description": "עלה על ערי יהודה הבצורות וצר על ירושלים בימי חזקיהו — ובנס מתו במחנהו 185,000 איש והוא שב בבושת פנים."
  },
  {
    "id": "necho",
    "name": "פרעה נכה מלך מצרים",
    "empire": "מצרים",
    "power": "egypt",
    "start": 3306,
    "end": 3330,
    "source": "מלכים ב כ\"ג",
    "description": "בעלותו למלחמה הרג את יאשיהו במגידו, הדיח את יהואחז והמליך את יהויקים ככפוף למצרים."
  },
  {
    "id": "nevuchadnetzar",
    "name": "נבוכדנצר מלך בבל",
    "empire": "בבל",
    "power": "babylon",
    "start": 3319,
    "end": 3364,
    "source": "מלכים ב כ\"ד–כ\"ה; דניאל",
    "description": "הגלה את יהויכין (3327) ובשנת 3338 החריב את בית המקדש הראשון והגלה את יהודה לבבל. בחלומותיו ובגורל דניאל וחבריו."
  },
  {
    "id": "belshatzar",
    "name": "בלשאצר מלך בבל",
    "empire": "בבל",
    "power": "babylon",
    "start": 3384,
    "end": 3389,
    "source": "דניאל ה'",
    "description": "מזרע נבוכדנצר. במשתה שבו חילל את כלי המקדש נגלתה הכתובת 'מנא מנא תקל ופרסין' — ובו בלילה נפלה בבל."
  },
  {
    "id": "koresh-w",
    "name": "כורש מלך פרס",
    "empire": "פרס",
    "power": "persia",
    "start": 3389,
    "end": 3393,
    "source": "עזרא א'; דברי הימים ב ל\"ו",
    "description": "מלך פרס שנתן רשות לשוב ולבנות את בית המקדש — 'מי בכם מכל עמו... ויעל לירושלים'."
  },
  {
    "id": "achashverosh",
    "name": "אחשורוש מלך פרס",
    "empire": "פרס",
    "power": "persia",
    "start": 3393,
    "end": 3406,
    "source": "מגילת אסתר",
    "description": "המולך מהודו ועד כוש — בימיו אירע נס פורים והצלת היהודים מגזירת המן."
  },
  {
    "id": "daryavesh",
    "name": "דריווש מלך פרס",
    "empire": "פרס",
    "power": "persia",
    "start": 3406,
    "end": 3413,
    "source": "עזרא ו'",
    "description": "בימיו הושלם בניין בית המקדש השני (3412) לאחר שאישר מחדש את הבנייה."
  },
  {
    "id": "alexander-w",
    "name": "אלכסנדר מוקדון",
    "empire": "יוון",
    "power": "greece",
    "start": 3442,
    "end": 3450,
    "source": "יומא סט.",
    "description": "כבש את האימפריה הפרסית וסיים את התקופה הפרסית; לפי המסורת חלק כבוד לשמעון הצדיק ולא פגע במקדש."
  },
  {
    "id": "antiochus",
    "name": "אנטיוכוס הרשע (יוון)",
    "empire": "יוון",
    "power": "greece",
    "start": 3588,
    "end": 3599,
    "source": "מגילת אנטיוכוס; ספר מקבים",
    "description": "גזר גזירות שמד וחילל את המקדש — וכנגדו קמו החשמונאים; נס חנוכה וטיהור המקדש."
  },
  {
    "id": "titus",
    "name": "טיטוס (רומא)",
    "empire": "רומא",
    "power": "rome",
    "start": 3820,
    "end": 3831,
    "source": "מלחמות היהודים (יוסף בן מתתיהו)",
    "description": "המצביא הרומי שהחריב את ירושלים ואת בית המקדש השני בשנת 3828 והגלה את העם לגלות הארוכה."
  }
]
